{"primaryContentSections":[{"declarations":[{"languages":["swift"],"tokens":[{"kind":"keyword","text":"enum"},{"kind":"text","text":" "},{"kind":"identifier","text":"JSONReference"},{"kind":"text","text":"<"},{"kind":"genericParameter","text":"ReferenceType"},{"kind":"text","text":"> "},{"kind":"keyword","text":"where"},{"kind":"text","text":" "},{"kind":"typeIdentifier","text":"ReferenceType"},{"kind":"text","text":" : "},{"kind":"typeIdentifier","identifier":"doc:\/\/OpenAPIKit\/documentation\/OpenAPIKit\/ComponentDictionaryLocatable","preciseIdentifier":"s:10OpenAPIKit28ComponentDictionaryLocatableP","text":"ComponentDictionaryLocatable"}],"platforms":["Linux"]}],"kind":"declarations"},{"kind":"content","content":[{"type":"heading","anchor":"overview","text":"Overview","level":2},{"type":"paragraph","inlineContent":[{"text":"These references are formatted like","type":"text"}]},{"type":"codeListing","syntax":null,"code":["$ref: filename.yml#\/path\/to\/something"]},{"type":"paragraph","inlineContent":[{"text":"The filename is omitted for internal references and the path","type":"text"},{"text":" ","type":"text"},{"text":"is not required for external references.","type":"text"}]},{"type":"paragraph","inlineContent":[{"text":"The intention, as prescribed by the OpenAPI specification, is","type":"text"},{"text":" ","type":"text"},{"text":"for this type to conform to the logic in the","type":"text"},{"text":" ","type":"text"},{"isActive":true,"type":"reference","identifier":"https:\/\/tools.ietf.org\/html\/draft-pbryan-zyp-json-ref-03"},{"text":".","type":"text"}]},{"type":"paragraph","inlineContent":[{"text":"A common reason to use ","type":"text"},{"code":"JSONReferences","type":"codeVoice"},{"text":" is to refer to","type":"text"},{"text":" ","type":"text"},{"text":"something in the OpenAPI Components Object. There are two","type":"text"},{"text":" ","type":"text"},{"text":"easy ways to create this kind of reference.","type":"text"}]},{"type":"unorderedList","items":[{"content":[{"inlineContent":[{"text":"The ","type":"text"},{"code":"JSONReference.component(named:)","type":"codeVoice"},{"text":" static constructor.","type":"text"}],"type":"paragraph"}]},{"content":[{"inlineContent":[{"type":"text","text":"The "},{"type":"codeVoice","code":"OpenAPI.Components"},{"type":"text","text":" "},{"type":"codeVoice","code":"reference(named:ofType:)"},{"type":"text","text":" method."}],"type":"paragraph"}]}]},{"type":"paragraph","inlineContent":[{"type":"text","text":"Which you use depends on your specifc needs. The "},{"type":"codeVoice","code":"reference(named:ofType:)"},{"type":"text","text":" "},{"type":"text","text":"method will guarantee that the thing you are referencing exists in the Components"},{"type":"text","text":" "},{"type":"text","text":"Object (or else the method will "},{"type":"codeVoice","code":"throw"},{"type":"text","text":" an error). The "},{"type":"codeVoice","code":"component(named:)"},{"type":"text","text":" "},{"type":"text","text":"constructor by contrast will not guarantee that the component you are referencing"},{"type":"text","text":" "},{"type":"text","text":"currently exists in the Components Object. The lack of safety might be beneficial"},{"type":"text","text":" "},{"type":"text","text":"or necessary depending on whether you have the Components Object built out and"},{"type":"text","text":" "},{"type":"text","text":"available at the time and location where you need to create a reference."}]},{"type":"paragraph","inlineContent":[{"type":"text","text":"Regardless of how you create your reference, internal references to things in the"},{"type":"text","text":" "},{"type":"text","text":"Components Object will be validated when you call "},{"type":"codeVoice","code":"validate()"},{"type":"text","text":" on an"},{"type":"text","text":" "},{"type":"codeVoice","code":"OpenAPI.Document"},{"type":"text","text":"."}]}]}],"hierarchy":{"paths":[["doc:\/\/OpenAPIKit\/documentation\/OpenAPIKit"]]},"relationshipsSections":[{"type":"conformsTo","kind":"relationships","title":"Conforms To","identifiers":["doc:\/\/OpenAPIKit\/documentation\/OpenAPIKit\/ExternallyDereferenceable","doc:\/\/OpenAPIKit\/documentation\/OpenAPIKit\/LocallyDereferenceable","doc:\/\/OpenAPIKit\/Se","doc:\/\/OpenAPIKit\/SE","doc:\/\/OpenAPIKit\/SQ","doc:\/\/OpenAPIKit\/SH","doc:\/\/OpenAPIKit\/s8SendableP"]}],"variants":[{"paths":["\/documentation\/openapikit\/jsonreference"],"traits":[{"interfaceLanguage":"swift"}]}],"topicSections":[{"title":"Structures","identifiers":["doc:\/\/OpenAPIKit\/documentation\/OpenAPIKit\/JSONReference\/Path","doc:\/\/OpenAPIKit\/documentation\/OpenAPIKit\/JSONReference\/PathComponent"]},{"title":"Enumeration Cases","identifiers":["doc:\/\/OpenAPIKit\/documentation\/OpenAPIKit\/JSONReference\/external(_:)","doc:\/\/OpenAPIKit\/documentation\/OpenAPIKit\/JSONReference\/internal(_:)"]},{"title":"Instance Properties","identifiers":["doc:\/\/OpenAPIKit\/documentation\/OpenAPIKit\/JSONReference\/absoluteString","doc:\/\/OpenAPIKit\/documentation\/OpenAPIKit\/JSONReference\/externalValue","doc:\/\/OpenAPIKit\/documentation\/OpenAPIKit\/JSONReference\/internalValue","doc:\/\/OpenAPIKit\/documentation\/OpenAPIKit\/JSONReference\/isExternal","doc:\/\/OpenAPIKit\/documentation\/OpenAPIKit\/JSONReference\/isInternal","doc:\/\/OpenAPIKit\/documentation\/OpenAPIKit\/JSONReference\/name"]},{"title":"Instance Methods","identifiers":["doc:\/\/OpenAPIKit\/documentation\/OpenAPIKit\/JSONReference\/openAPIReference(withDescription:)"]},{"title":"Type Methods","identifiers":["doc:\/\/OpenAPIKit\/documentation\/OpenAPIKit\/JSONReference\/component(named:)","doc:\/\/OpenAPIKit\/documentation\/OpenAPIKit\/JSONReference\/internal(path:)"]},{"title":"Enumerations","identifiers":["doc:\/\/OpenAPIKit\/documentation\/OpenAPIKit\/JSONReference\/InternalReference"]},{"generated":true,"title":"Default Implementations","identifiers":["doc:\/\/OpenAPIKit\/documentation\/OpenAPIKit\/JSONReference\/Decodable-Implementations","doc:\/\/OpenAPIKit\/documentation\/OpenAPIKit\/JSONReference\/Encodable-Implementations","doc:\/\/OpenAPIKit\/documentation\/OpenAPIKit\/JSONReference\/Equatable-Implementations","doc:\/\/OpenAPIKit\/documentation\/OpenAPIKit\/JSONReference\/ExternallyDereferenceable-Implementations","doc:\/\/OpenAPIKit\/documentation\/OpenAPIKit\/JSONReference\/LocallyDereferenceable-Implementations"]}],"metadata":{"roleHeading":"Enumeration","symbolKind":"enum","role":"symbol","modules":[{"name":"OpenAPIKit"}],"title":"JSONReference","externalID":"s:10OpenAPIKit13JSONReferenceO","navigatorTitle":[{"kind":"identifier","text":"JSONReference"}],"fragments":[{"text":"enum","kind":"keyword"},{"text":" ","kind":"text"},{"text":"JSONReference","kind":"identifier"}]},"kind":"symbol","schemaVersion":{"minor":3,"major":0,"patch":0},"sections":[],"identifier":{"url":"doc:\/\/OpenAPIKit\/documentation\/OpenAPIKit\/JSONReference","interfaceLanguage":"swift"},"abstract":[{"type":"text","text":"A reference following the JSON Reference specification."}],"references":{"doc://OpenAPIKit/documentation/OpenAPIKit/LocallyDereferenceable":{"identifier":"doc:\/\/OpenAPIKit\/documentation\/OpenAPIKit\/LocallyDereferenceable","type":"topic","role":"symbol","navigatorTitle":[{"kind":"identifier","text":"LocallyDereferenceable"}],"title":"LocallyDereferenceable","url":"\/documentation\/openapikit\/locallydereferenceable","conformance":{"constraints":[{"type":"codeVoice","code":"ReferenceType"},{"text":" conforms to ","type":"text"},{"type":"codeVoice","code":"ComponentDictionaryLocatable"},{"text":" and ","type":"text"},{"type":"codeVoice","code":"LocallyDereferenceable"},{"text":".","type":"text"}],"availabilityPrefix":[{"text":"Available when","type":"text"}],"conformancePrefix":[{"text":"Conforms when","type":"text"}]},"kind":"symbol","abstract":[{"type":"text","text":"A dereferenceable type can be recursively looked up in"},{"type":"text","text":" "},{"type":"text","text":"the "},{"code":"OpenAPI.Components","type":"codeVoice"},{"type":"text","text":" until there are no "},{"code":"OpenAPI.References","type":"codeVoice"},{"type":"text","text":" "},{"type":"text","text":"left in it or any of its properties."}],"fragments":[{"kind":"keyword","text":"protocol"},{"kind":"text","text":" "},{"kind":"identifier","text":"LocallyDereferenceable"}]},"https://tools.ietf.org/html/draft-pbryan-zyp-json-ref-03":{"titleInlineContent":[{"text":"JSON Reference spec","type":"text"}],"title":"JSON Reference spec","type":"link","url":"https:\/\/tools.ietf.org\/html\/draft-pbryan-zyp-json-ref-03","identifier":"https:\/\/tools.ietf.org\/html\/draft-pbryan-zyp-json-ref-03"},"doc://OpenAPIKit/documentation/OpenAPIKit/JSONReference/PathComponent":{"identifier":"doc:\/\/OpenAPIKit\/documentation\/OpenAPIKit\/JSONReference\/PathComponent","role":"symbol","title":"JSONReference.PathComponent","url":"\/documentation\/openapikit\/jsonreference\/pathcomponent","abstract":[{"text":"A JSON Reference path component, as described by the ","type":"text"},{"identifier":"https:\/\/tools.ietf.org\/html\/draft-ietf-appsawg-json-pointer-04","type":"reference","isActive":true},{"text":".","type":"text"}],"kind":"symbol","navigatorTitle":[{"text":"PathComponent","kind":"identifier"}],"type":"topic","fragments":[{"text":"struct","kind":"keyword"},{"text":" ","kind":"text"},{"text":"PathComponent","kind":"identifier"}]},"doc://OpenAPIKit/documentation/OpenAPIKit/JSONReference/external(_:)":{"title":"JSONReference.external(_:)","type":"topic","kind":"symbol","fragments":[{"kind":"keyword","text":"case"},{"kind":"text","text":" "},{"kind":"identifier","text":"external"},{"kind":"text","text":"("},{"kind":"typeIdentifier","text":"URL","preciseIdentifier":"s:10Foundation3URLV"},{"kind":"text","text":")"}],"url":"\/documentation\/openapikit\/jsonreference\/external(_:)","role":"symbol","identifier":"doc:\/\/OpenAPIKit\/documentation\/OpenAPIKit\/JSONReference\/external(_:)","abstract":[{"type":"text","text":"The reference refers to another file."}]},"doc://OpenAPIKit/documentation/OpenAPIKit/JSONReference/name":{"identifier":"doc:\/\/OpenAPIKit\/documentation\/OpenAPIKit\/JSONReference\/name","type":"topic","role":"symbol","title":"name","url":"\/documentation\/openapikit\/jsonreference\/name","kind":"symbol","abstract":[{"type":"text","text":"Get the name of the referenced object. This method returns optional"},{"type":"text","text":" "},{"type":"text","text":"because a reference to an external file might not have any path if the"},{"type":"text","text":" "},{"type":"text","text":"file itself is the referenced component."}],"fragments":[{"kind":"keyword","text":"var"},{"kind":"text","text":" "},{"kind":"identifier","text":"name"},{"kind":"text","text":": "},{"kind":"typeIdentifier","text":"String","preciseIdentifier":"s:SS"},{"kind":"text","text":"?"}]},"doc://OpenAPIKit/documentation/OpenAPIKit/ExternallyDereferenceable":{"identifier":"doc:\/\/OpenAPIKit\/documentation\/OpenAPIKit\/ExternallyDereferenceable","role":"symbol","title":"ExternallyDereferenceable","url":"\/documentation\/openapikit\/externallydereferenceable","conformance":{"conformancePrefix":[{"type":"text","text":"Conforms when"}],"availabilityPrefix":[{"type":"text","text":"Available when"}],"constraints":[{"code":"ReferenceType","type":"codeVoice"},{"type":"text","text":" conforms to "},{"code":"ComponentDictionaryLocatable","type":"codeVoice"},{"type":"text","text":", "},{"type":"codeVoice","code":"ExternallyDereferenceable"},{"type":"text","text":", "},{"type":"codeVoice","code":"Decodable"},{"text":", and ","type":"text"},{"type":"codeVoice","code":"Equatable"},{"text":".","type":"text"}]},"abstract":[],"kind":"symbol","navigatorTitle":[{"kind":"identifier","text":"ExternallyDereferenceable"}],"type":"topic","fragments":[{"kind":"keyword","text":"protocol"},{"kind":"text","text":" "},{"kind":"identifier","text":"ExternallyDereferenceable"}]},"doc://OpenAPIKit/documentation/OpenAPIKit/JSONReference/component(named:)":{"url":"\/documentation\/openapikit\/jsonreference\/component(named:)","fragments":[{"kind":"keyword","text":"static"},{"kind":"text","text":" "},{"kind":"keyword","text":"func"},{"kind":"text","text":" "},{"kind":"identifier","text":"component"},{"kind":"text","text":"("},{"kind":"externalParam","text":"named"},{"kind":"text","text":": "},{"kind":"typeIdentifier","text":"String","preciseIdentifier":"s:SS"},{"text":") -> ","kind":"text"},{"text":"JSONReference","kind":"typeIdentifier","preciseIdentifier":"s:10OpenAPIKit13JSONReferenceO"},{"kind":"text","text":"<"},{"kind":"typeIdentifier","text":"ReferenceType"},{"kind":"text","text":">"}],"identifier":"doc:\/\/OpenAPIKit\/documentation\/OpenAPIKit\/JSONReference\/component(named:)","type":"topic","role":"symbol","abstract":[{"type":"text","text":"Reference a component of type "},{"type":"codeVoice","code":"ReferenceType"},{"type":"text","text":" in the"},{"type":"text","text":" "},{"type":"text","text":"Components Object."}],"kind":"symbol","title":"component(named:)"},"doc://OpenAPIKit/documentation/OpenAPIKit/JSONReference/Encodable-Implementations":{"type":"topic","kind":"article","role":"collectionGroup","url":"\/documentation\/openapikit\/jsonreference\/encodable-implementations","title":"Encodable Implementations","identifier":"doc:\/\/OpenAPIKit\/documentation\/OpenAPIKit\/JSONReference\/Encodable-Implementations","abstract":[]},"https://tools.ietf.org/html/rfc3986":{"titleInlineContent":[{"type":"text","text":"RFC 3986"}],"title":"RFC 3986","type":"link","url":"https:\/\/tools.ietf.org\/html\/rfc3986","identifier":"https:\/\/tools.ietf.org\/html\/rfc3986"},"doc://OpenAPIKit/SE":{"type":"unresolvable","title":"Swift.Encodable","identifier":"doc:\/\/OpenAPIKit\/SE"},"doc://OpenAPIKit/documentation/OpenAPIKit":{"type":"topic","title":"OpenAPIKit","role":"collection","kind":"symbol","identifier":"doc:\/\/OpenAPIKit\/documentation\/OpenAPIKit","url":"\/documentation\/openapikit","abstract":[]},"doc://OpenAPIKit/documentation/OpenAPIKit/JSONReference/Decodable-Implementations":{"identifier":"doc:\/\/OpenAPIKit\/documentation\/OpenAPIKit\/JSONReference\/Decodable-Implementations","role":"collectionGroup","title":"Decodable Implementations","url":"\/documentation\/openapikit\/jsonreference\/decodable-implementations","abstract":[],"kind":"article","type":"topic"},"doc://OpenAPIKit/documentation/OpenAPIKit/JSONReference/isInternal":{"url":"\/documentation\/openapikit\/jsonreference\/isinternal","fragments":[{"kind":"keyword","text":"var"},{"kind":"text","text":" "},{"kind":"identifier","text":"isInternal"},{"kind":"text","text":": "},{"kind":"typeIdentifier","text":"Bool","preciseIdentifier":"s:Sb"}],"identifier":"doc:\/\/OpenAPIKit\/documentation\/OpenAPIKit\/JSONReference\/isInternal","type":"topic","role":"symbol","abstract":[{"code":"true","type":"codeVoice"},{"type":"text","text":" for internal references, "},{"code":"false","type":"codeVoice"},{"type":"text","text":" for"},{"type":"text","text":" "},{"type":"text","text":"external references (i.e. to another file)."}],"kind":"symbol","title":"isInternal"},"doc://OpenAPIKit/documentation/OpenAPIKit/JSONReference/Path":{"type":"topic","fragments":[{"kind":"keyword","text":"struct"},{"kind":"text","text":" "},{"kind":"identifier","text":"Path"}],"navigatorTitle":[{"kind":"identifier","text":"Path"}],"kind":"symbol","role":"symbol","url":"\/documentation\/openapikit\/jsonreference\/path","title":"JSONReference.Path","identifier":"doc:\/\/OpenAPIKit\/documentation\/OpenAPIKit\/JSONReference\/Path","abstract":[{"type":"text","text":"A JSON Reference path."}]},"doc://OpenAPIKit/documentation/OpenAPIKit/JSONReference/absoluteString":{"identifier":"doc:\/\/OpenAPIKit\/documentation\/OpenAPIKit\/JSONReference\/absoluteString","role":"symbol","title":"absoluteString","url":"\/documentation\/openapikit\/jsonreference\/absolutestring","abstract":[{"type":"text","text":"The absolute value of an external reference’s"},{"type":"text","text":" "},{"type":"text","text":"URL or the path fragment string for a local"},{"type":"text","text":" "},{"type":"text","text":"reference as defined in "},{"isActive":true,"type":"reference","identifier":"https:\/\/tools.ietf.org\/html\/rfc3986"},{"type":"text","text":"."}],"kind":"symbol","type":"topic","fragments":[{"kind":"keyword","text":"var"},{"kind":"text","text":" "},{"kind":"identifier","text":"absoluteString"},{"kind":"text","text":": "},{"preciseIdentifier":"s:SS","kind":"typeIdentifier","text":"String"}]},"doc://OpenAPIKit/s8SendableP":{"title":"Swift.Sendable","type":"unresolvable","identifier":"doc:\/\/OpenAPIKit\/s8SendableP"},"doc://OpenAPIKit/documentation/OpenAPIKit/JSONReference/openAPIReference(withDescription:)":{"type":"topic","fragments":[{"kind":"keyword","text":"func"},{"kind":"text","text":" "},{"kind":"identifier","text":"openAPIReference"},{"kind":"text","text":"("},{"kind":"externalParam","text":"withDescription"},{"kind":"text","text":": "},{"preciseIdentifier":"s:SS","kind":"typeIdentifier","text":"String"},{"kind":"text","text":"?) -> "},{"preciseIdentifier":"s:10OpenAPIKit0A3APIO","kind":"typeIdentifier","text":"OpenAPI"},{"kind":"text","text":"."},{"preciseIdentifier":"s:10OpenAPIKit0A3APIO9ReferenceV","kind":"typeIdentifier","text":"Reference"},{"kind":"text","text":"<"},{"kind":"typeIdentifier","text":"ReferenceType"},{"kind":"text","text":">"}],"kind":"symbol","role":"symbol","conformance":{"constraints":[{"type":"codeVoice","code":"ReferenceType"},{"type":"text","text":" conforms to "},{"type":"codeVoice","code":"ComponentDictionaryLocatable"},{"type":"text","text":"."}],"availabilityPrefix":[{"type":"text","text":"Available when"}],"conformancePrefix":[{"type":"text","text":"Conforms when"}]},"url":"\/documentation\/openapikit\/jsonreference\/openapireference(withdescription:)","title":"openAPIReference(withDescription:)","identifier":"doc:\/\/OpenAPIKit\/documentation\/OpenAPIKit\/JSONReference\/openAPIReference(withDescription:)","abstract":[{"type":"text","text":"Create an OpenAPI.Reference from the given JSONReference."}]},"doc://OpenAPIKit/documentation/OpenAPIKit/JSONReference/internal(path:)":{"url":"\/documentation\/openapikit\/jsonreference\/internal(path:)","fragments":[{"kind":"keyword","text":"static"},{"kind":"text","text":" "},{"kind":"keyword","text":"func"},{"kind":"text","text":" "},{"kind":"identifier","text":"`internal`"},{"kind":"text","text":"("},{"kind":"externalParam","text":"path"},{"kind":"text","text":": "},{"kind":"typeIdentifier","text":"JSONReference","preciseIdentifier":"s:10OpenAPIKit13JSONReferenceO"},{"kind":"text","text":"<"},{"kind":"typeIdentifier","text":"ReferenceType"},{"kind":"text","text":">."},{"text":"Path","kind":"typeIdentifier","preciseIdentifier":"s:10OpenAPIKit13JSONReferenceO4PathV"},{"text":") -> ","kind":"text"},{"text":"JSONReference","kind":"typeIdentifier","preciseIdentifier":"s:10OpenAPIKit13JSONReferenceO"},{"text":"<","kind":"text"},{"text":"ReferenceType","kind":"typeIdentifier"},{"text":">","kind":"text"}],"identifier":"doc:\/\/OpenAPIKit\/documentation\/OpenAPIKit\/JSONReference\/internal(path:)","type":"topic","role":"symbol","abstract":[{"type":"text","text":"Reference a path internal to this file but not within the Components Object"},{"type":"text","text":" "},{"type":"text","text":"This is likely not what you are looking for. It is advisable to store reusable components"},{"type":"text","text":" "},{"type":"text","text":"in the Components Object."}],"kind":"symbol","title":"internal(path:)"},"doc://OpenAPIKit/documentation/OpenAPIKit/JSONReference/LocallyDereferenceable-Implementations":{"type":"topic","kind":"article","role":"collectionGroup","url":"\/documentation\/openapikit\/jsonreference\/locallydereferenceable-implementations","title":"LocallyDereferenceable Implementations","identifier":"doc:\/\/OpenAPIKit\/documentation\/OpenAPIKit\/JSONReference\/LocallyDereferenceable-Implementations","abstract":[]},"doc://OpenAPIKit/SQ":{"title":"Swift.Equatable","type":"unresolvable","identifier":"doc:\/\/OpenAPIKit\/SQ"},"doc://OpenAPIKit/documentation/OpenAPIKit/JSONReference/InternalReference":{"type":"topic","fragments":[{"kind":"keyword","text":"enum"},{"kind":"text","text":" "},{"kind":"identifier","text":"InternalReference"}],"navigatorTitle":[{"kind":"identifier","text":"InternalReference"}],"kind":"symbol","role":"symbol","url":"\/documentation\/openapikit\/jsonreference\/internalreference","title":"JSONReference.InternalReference","identifier":"doc:\/\/OpenAPIKit\/documentation\/OpenAPIKit\/JSONReference\/InternalReference","abstract":[{"type":"text","text":"The context for a JSONReference that points to something within"},{"type":"text","text":" "},{"type":"text","text":"the same document as the reference itself."}]},"doc://OpenAPIKit/documentation/OpenAPIKit/JSONReference/isExternal":{"title":"isExternal","type":"topic","kind":"symbol","fragments":[{"kind":"keyword","text":"var"},{"kind":"text","text":" "},{"kind":"identifier","text":"isExternal"},{"kind":"text","text":": "},{"kind":"typeIdentifier","text":"Bool","preciseIdentifier":"s:Sb"}],"url":"\/documentation\/openapikit\/jsonreference\/isexternal","role":"symbol","identifier":"doc:\/\/OpenAPIKit\/documentation\/OpenAPIKit\/JSONReference\/isExternal","abstract":[{"code":"true","type":"codeVoice"},{"type":"text","text":" for external references, "},{"code":"false","type":"codeVoice"},{"type":"text","text":" for"},{"type":"text","text":" "},{"type":"text","text":"internal references."}]},"doc://OpenAPIKit/documentation/OpenAPIKit/JSONReference/Equatable-Implementations":{"identifier":"doc:\/\/OpenAPIKit\/documentation\/OpenAPIKit\/JSONReference\/Equatable-Implementations","role":"collectionGroup","title":"Equatable Implementations","url":"\/documentation\/openapikit\/jsonreference\/equatable-implementations","abstract":[],"kind":"article","type":"topic"},"doc://OpenAPIKit/documentation/OpenAPIKit/JSONReference":{"identifier":"doc:\/\/OpenAPIKit\/documentation\/OpenAPIKit\/JSONReference","role":"symbol","title":"JSONReference","url":"\/documentation\/openapikit\/jsonreference","abstract":[{"text":"A reference following the JSON Reference specification.","type":"text"}],"kind":"symbol","navigatorTitle":[{"text":"JSONReference","kind":"identifier"}],"type":"topic","fragments":[{"text":"enum","kind":"keyword"},{"text":" ","kind":"text"},{"text":"JSONReference","kind":"identifier"}]},"doc://OpenAPIKit/documentation/OpenAPIKit/ComponentDictionaryLocatable":{"abstract":[{"text":"Anything conforming to ComponentDictionaryLocatable knows","type":"text"},{"text":" ","type":"text"},{"text":"where to find resources of its type in the Components Dictionary.","type":"text"}],"kind":"symbol","navigatorTitle":[{"kind":"identifier","text":"ComponentDictionaryLocatable"}],"fragments":[{"kind":"keyword","text":"protocol"},{"kind":"text","text":" "},{"text":"ComponentDictionaryLocatable","kind":"identifier"}],"identifier":"doc:\/\/OpenAPIKit\/documentation\/OpenAPIKit\/ComponentDictionaryLocatable","type":"topic","title":"ComponentDictionaryLocatable","url":"\/documentation\/openapikit\/componentdictionarylocatable","role":"symbol"},"doc://OpenAPIKit/documentation/OpenAPIKit/JSONReference/externalValue":{"type":"topic","fragments":[{"kind":"keyword","text":"var"},{"kind":"text","text":" "},{"kind":"identifier","text":"externalValue"},{"kind":"text","text":": "},{"kind":"typeIdentifier","text":"URL","preciseIdentifier":"s:10Foundation3URLV"},{"kind":"text","text":"?"}],"kind":"symbol","role":"symbol","url":"\/documentation\/openapikit\/jsonreference\/externalvalue","title":"externalValue","identifier":"doc:\/\/OpenAPIKit\/documentation\/OpenAPIKit\/JSONReference\/externalValue","abstract":[{"type":"text","text":"Get the external value if this reference is external. Otherwise, nil."}]},"https://tools.ietf.org/html/draft-ietf-appsawg-json-pointer-04":{"identifier":"https:\/\/tools.ietf.org\/html\/draft-ietf-appsawg-json-pointer-04","title":"JSON pointer specification","url":"https:\/\/tools.ietf.org\/html\/draft-ietf-appsawg-json-pointer-04","titleInlineContent":[{"text":"JSON pointer specification","type":"text"}],"type":"link"},"doc://OpenAPIKit/documentation/OpenAPIKit/JSONReference/ExternallyDereferenceable-Implementations":{"url":"\/documentation\/openapikit\/jsonreference\/externallydereferenceable-implementations","identifier":"doc:\/\/OpenAPIKit\/documentation\/OpenAPIKit\/JSONReference\/ExternallyDereferenceable-Implementations","type":"topic","role":"collectionGroup","abstract":[],"kind":"article","title":"ExternallyDereferenceable Implementations"},"doc://OpenAPIKit/Se":{"title":"Swift.Decodable","type":"unresolvable","identifier":"doc:\/\/OpenAPIKit\/Se"},"doc://OpenAPIKit/documentation/OpenAPIKit/JSONReference/internalValue":{"url":"\/documentation\/openapikit\/jsonreference\/internalvalue","fragments":[{"kind":"keyword","text":"var"},{"kind":"text","text":" "},{"kind":"identifier","text":"internalValue"},{"kind":"text","text":": "},{"preciseIdentifier":"s:10OpenAPIKit13JSONReferenceO","kind":"typeIdentifier","text":"JSONReference"},{"kind":"text","text":"<"},{"kind":"typeIdentifier","text":"ReferenceType"},{"kind":"text","text":">."},{"preciseIdentifier":"s:10OpenAPIKit13JSONReferenceO17InternalReferenceO","kind":"typeIdentifier","text":"InternalReference"},{"kind":"text","text":"?"}],"identifier":"doc:\/\/OpenAPIKit\/documentation\/OpenAPIKit\/JSONReference\/internalValue","type":"topic","role":"symbol","abstract":[{"type":"text","text":"Get the internal value if this reference is internal. Otherwise, nil."}],"kind":"symbol","title":"internalValue"},"doc://OpenAPIKit/SH":{"title":"Swift.Hashable","type":"unresolvable","identifier":"doc:\/\/OpenAPIKit\/SH"},"doc://OpenAPIKit/documentation/OpenAPIKit/JSONReference/internal(_:)":{"identifier":"doc:\/\/OpenAPIKit\/documentation\/OpenAPIKit\/JSONReference\/internal(_:)","role":"symbol","title":"JSONReference.internal(_:)","url":"\/documentation\/openapikit\/jsonreference\/internal(_:)","abstract":[{"type":"text","text":"The reference is internal to the file."}],"kind":"symbol","type":"topic","fragments":[{"kind":"keyword","text":"case"},{"kind":"text","text":" "},{"kind":"identifier","text":"`internal`"},{"kind":"text","text":"("},{"preciseIdentifier":"s:10OpenAPIKit13JSONReferenceO","kind":"typeIdentifier","text":"JSONReference"},{"kind":"text","text":"<"},{"kind":"typeIdentifier","text":"ReferenceType"},{"kind":"text","text":">."},{"preciseIdentifier":"s:10OpenAPIKit13JSONReferenceO17InternalReferenceO","kind":"typeIdentifier","text":"InternalReference"},{"kind":"text","text":")"}]}}}